hugo2llmtxt.py
hugo2llmtxt-0.1.4.dist-info/METADATA
hugo2llmtxt-0.1.4.dist-info/WHEEL
hugo2llmtxt-0.1.4.dist-info/entry_points.txt
hugo2llmtxt-0.1.4.dist-info/top_level.txt
hugo2llmtxt-0.1.4.dist-info/RECORD
