Metadata-Version: 2.2
Name: hugo2llmtxt
Version: 0.1.4
Summary: Generate the llms.txt file for the hugo website
Requires-Python: >=3.12
Requires-Dist: typer>=0.15.1
